logelin/__init__.py
logelin/convert.py
logelin/infer.py
logelin-0.2.2.dist-info/METADATA
logelin-0.2.2.dist-info/WHEEL
logelin-0.2.2.dist-info/top_level.txt
logelin-0.2.2.dist-info/RECORD
