Metadata-Version: 2.1
Name: logelin
Version: 0.2.2
Summary: A tool which, by modelling the sampled galaxies as ellipsoids with intrinsic semi-axes drawn from a multivariate log-normal distribution, uses Bayesian inference to generate posteriors for parameters describing the underlying distribution of shapes and sizes of galaxies given projected angular extents and redshifts. Built using NumPyro and astropy.
Home-page: https://github.com/dmjwentworth/lognormal-ellipsoid-inferrer
Author: Dougal Wentworth
Author-email: dw619@cantab.ac.uk
License: MIT license
Classifier: Development Status :: 1 - Planning
Classifier: Intended Audience :: Science/Research
Classifier: License :: OSI Approved :: MIT License
Classifier: Programming Language :: Python :: 3.11
Requires-Dist: jax
Requires-Dist: astropy
Requires-Dist: numpyro
Requires-Dist: matplotlib
